ifitpy/Fitter.py
ifitpy/Histograms.py
ifitpy/__init__.py
ifitpy-0.0.8.dist-info/LICENSE.txt
ifitpy-0.0.8.dist-info/METADATA
ifitpy-0.0.8.dist-info/WHEEL
ifitpy-0.0.8.dist-info/top_level.txt
ifitpy-0.0.8.dist-info/RECORD
