Metadata-Version: 2.2
Name: ifitpy
Version: 0.0.8
Summary: Simple data fitting package
Home-page: https://https://github.com/gpinpereira/Pyfit
Download-URL: https://github.com/gpinpereira/Pyfit/archive/refs/tags/0.0.1.tar.gz
Author: Guilherme Pereira
Author-email: Guilherme Pereira <guipinper@gmail.com>
License: MIT
Project-URL: Homepage, https://github.com/gpinpereira/Pyfit
Project-URL: Bug Tracker, https://github.com/gpinpereira/Pyfit/issues
Keywords: fitting,datascience,iminuit
Classifier: Development Status :: 3 - Alpha
Classifier: Intended Audience :: Developers
Classifier: Topic :: Software Development :: Documentation
Classifier: License :: OSI Approved :: MIT License
Classifier: Programming Language :: Python :: 3
Classifier: Programming Language :: Python :: 3.7
Classifier: Programming Language :: Python :: 3.8
Classifier: Programming Language :: Python :: 3.9
License-File: LICENSE.txt
Requires-Dist: numpy
Requires-Dist: scipy
Dynamic: author
Dynamic: download-url
Dynamic: home-page
